funk_py/__init__.py
funk_py/modularity/__init__.py
funk_py/modularity/basic_structures.py
funk_py/modularity/bespoke_properties.py
funk_py/modularity/logging.py
funk_py/modularity/type_matching.py
funk_py/modularity/decoration/__init__.py
funk_py/modularity/decoration/cache_modifiers.py
funk_py/modularity/decoration/enums.py
funk_py/modularity/decoration/init_modifiers.py
funk_py/modularity/decoration/method_modifiers.py
funk_py/modularity/decoration/transforming_list.py
funk_py/sorting/__init__.py
funk_py/sorting/converters.py
funk_py/sorting/dict_manip.py
funk_py/sorting/pieces.py
funk_py/super_dicts/__init__.py
funk_py/super_dicts/drop_none_dict.py
funk_py/super_dicts/list_dict.py
funk_py/super_dicts/windowed_list.py
funky_modifiers-0.5.1.dist-info/LICENSE
funky_modifiers-0.5.1.dist-info/METADATA
funky_modifiers-0.5.1.dist-info/WHEEL
funky_modifiers-0.5.1.dist-info/top_level.txt
funky_modifiers-0.5.1.dist-info/RECORD
